python4kyoani/__init__.py
python4kyoani/image.py
python4kyoani/util.py
python4kyoani-0.9.2.dist-info/LICENSE
python4kyoani-0.9.2.dist-info/METADATA
python4kyoani-0.9.2.dist-info/WHEEL
python4kyoani-0.9.2.dist-info/entry_points.txt
python4kyoani-0.9.2.dist-info/top_level.txt
python4kyoani-0.9.2.dist-info/RECORD
