Metadata-Version: 2.1
Name: python4kyoani
Version: 0.9.2
Summary: 僕たちはPythonで京アニに何ができるだろうか
Home-page: https://github.com/ftnext/python4kyoani
License: MIT
Keywords: PrayForKyoani
Platform: UNKNOWN
Classifier: Programming Language :: Python :: 3
Classifier: Programming Language :: Python :: 3.7
Requires-Dist: Pillow (>=6.0)
Provides-Extra: dev
Requires-Dist: doc8 ; extra == 'dev'
Requires-Dist: flake8 ; extra == 'dev'
Requires-Dist: pytest ; extra == 'dev'
